{
  "run_name": "tile_baseline2__lodo_glue_strip",
  "category": "tile",
  "config": {
    "run_name": "tile_baseline2",
    "category": "tile",
    "backbone": "resnet50",
    "traditional_aug": true,
    "use_synthetic": false,
    "few_shot_n": null,
    "epochs": 30,
    "batch_size": 32,
    "lr": 0.0001,
    "holdout_defect_type": "glue_strip"
  },
  "device": "cuda",
  "epochs_run": 30,
  "best_val_auroc": 1.0,
  "threshold": 0.5168950539082289,
  "checkpoint": "experiments/checkpoints/tile_baseline2__lodo_glue_strip.pt",
  "metrics": {
    "accuracy": 1.0,
    "per_class": {
      "good": {
        "precision": 1.0,
        "recall": 1.0,
        "f1": 1.0,
        "support": 17
      },
      "defect": {
        "precision": 1.0,
        "recall": 1.0,
        "f1": 1.0,
        "support": 18
      }
    },
    "macro": {
      "precision": 1.0,
      "recall": 1.0,
      "f1": 1.0
    },
    "auroc": 1.0
  },
  "metrics_at_0p5": {
    "accuracy": 1.0,
    "per_class": {
      "good": {
        "precision": 1.0,
        "recall": 1.0,
        "f1": 1.0,
        "support": 17
      },
      "defect": {
        "precision": 1.0,
        "recall": 1.0,
        "f1": 1.0,
        "support": 18
      }
    },
    "macro": {
      "precision": 1.0,
      "recall": 1.0,
      "f1": 1.0
    },
    "auroc": 1.0
  },
  "timestamp": "2026-07-12T12:00:28"
}